archivkompakt/__init__.py
archivkompakt-1.0.1.dist-info/LICENSE.TXT
archivkompakt-1.0.1.dist-info/METADATA
archivkompakt-1.0.1.dist-info/WHEEL
archivkompakt-1.0.1.dist-info/top_level.txt
archivkompakt-1.0.1.dist-info/RECORD
