Metadata-Version: 2.1
Name: archivkompakt
Version: 1.0.1
Summary: Aareon Archiv Kompakt connector
Home-page: https://github.com/seb-bau/python-archivkompakt
Author: Sebastian Bauhaus
Author-email: sebastian@bytewish.de
License: MIT
Keywords: AAK,archiv kompakt,archivkompakt,aareon
Classifier: Development Status :: 5 - Production/Stable
Classifier: Intended Audience :: Developers
Classifier: License :: OSI Approved :: MIT License
Classifier: Operating System :: Unix
Classifier: Operating System :: Microsoft :: Windows
Classifier: Programming Language :: Python :: 3
Classifier: Programming Language :: Python :: 3.1
Classifier: Programming Language :: Python :: 3.2
Classifier: Programming Language :: Python :: 3.3
Classifier: Programming Language :: Python :: 3.4
Classifier: Programming Language :: Python :: 3.5
Classifier: Programming Language :: Python :: 3.6
Classifier: Programming Language :: Python :: 3.7
Classifier: Programming Language :: Python :: 3.8
Classifier: Programming Language :: Python :: 3.9
Classifier: Programming Language :: Python :: 3.10
Classifier: Programming Language :: Python :: 3.11
Requires-Python: >=3.0
License-File: LICENSE.TXT
Requires-Dist: requests (>=2.0)
